coadd/__init__.py
coadd/coadd.py
coadd-1.0.1.data/scripts/coadd
coadd-1.0.1.dist-info/LICENSE
coadd-1.0.1.dist-info/METADATA
coadd-1.0.1.dist-info/WHEEL
coadd-1.0.1.dist-info/top_level.txt
coadd-1.0.1.dist-info/RECORD
